Workbook

Sheet Assumptions
A1: Assumptions — RES Permit Cross-Checker
A3: Ministry: environment-energy Buyer: ΥΠΕΝ / ΡΑΑΕΥ
A5: PRICING
A6: Pricing | B6: Y1 | C6: Y2 | D6: Y3 | E6: Y4 | F6: Y5
A7: Tier 1 — pilot price (€) | B7: 90000 | C7: 90000 | D7: 90000 | E7: 90000 | F7: 90000
A8: Tier 2 — year-one ACV (€) | B8: 450000 | C8: 450000 | D8: 450000 | E8: 450000 | F8: 450000
A9: Tier 3 — framework ACV (€) | B9: 1400000 | C9: 1400000 | D9: 1400000 | E9: 1400000 | F9: 1400000
A10: Avg seats per Tier-2 customer | B10: 30 | C10: 30 | D10: 30 | E10: 30 | F10: 30
A11: Blended seat price (€/yr) | B11: 3000 | C11: 3000 | D11: 3000 | E11: 3000 | F11: 3000
A13: ADOPTION (count per year)
A14: Adoption | B14: Y1 | C14: Y2 | D14: Y3 | E14: Y4 | F14: Y5
A15: Tier 1 customers (new + active) | B15: 2 | C15: 3 | D15: 2 | E15: 0 | F15: 0
A16: Tier 2 customers (cumulative active) | B16: 0 | C16: 2 | D16: 5 | E16: 9 | F16: 14
A17: Tier 3 customers (cumulative active) | B17: 0 | C17: 0 | D17: 1 | E17: 2 | F17: 3
A19: HEADCOUNT (FTE per year)
A20: Role | B20: Y1 | C20: Y2 | D20: Y3 | E20: Y4 | F20: Y5
A21: Founders | B21: 3 | C21: 3 | D21: 3 | E21: 3 | F21: 3
A22: Engineering | B22: 2 | C22: 4 | D22: 7 | E22: 10 | F22: 14
A23: Product | B23: 0 | C23: 1 | D23: 1 | E23: 2 | F23: 2
A24: Sales | B24: 0 | C24: 1 | D24: 2 | E24: 3 | F24: 4
A25: Customer Success | B25: 0 | C25: 1 | D25: 2 | E25: 3 | F25: 4
A26: G&A | B26: 0 | C26: 1 | D26: 1 | E26: 2 | F26: 3
A27: Loaded €/FTE (Athens) | B27: 72000 | C27: 72000 | D27: 72000 | E27: 72000 | F27: 72000
A29: COGS & OPEX RATIOS
A30: Cost driver | B30: Y1 | C30: Y2 | D30: Y3 | E30: Y4 | F30: Y5
A31: Hosting €/customer/yr | B31: 8000 | C31: 8000 | D31: 8000 | E31: 8000 | F31: 8000
A32: S&M non-personnel (% of revenue) | B32: 0.1 | C32: 0.1 | D32: 0.1 | E32: 0.1 | F32: 0.1
A33: G&A non-personnel (% of revenue) | B33: 0.06 | C33: 0.06 | D33: 0.06 | E33: 0.06 | F33: 0.06
A34: Customer-success additional COGS (% of revenue) | B34: 0.05 | C34: 0.05 | D34: 0.05 | E34: 0.05 | F34: 0.05
A35: Gross margin target | B35: 0.72 | C35: 0.72 | D35: 0.72 | E35: 0.72 | F35: 0.72
A37: CAPITAL
A38: Pre-seed (€) | B38: 800000
A39: Pre-seed raise year | B39: 1
A40: Seed (€) | B40: 3500000
A41: Seed raise year | B41: 2
A42: Series A (€) | B42: 10000000
A43: Series A raise year | B43: 4

Sheet Revenue
A1: Revenue Build
A2: Revenue line | B2: Y1 | C2: Y2 | D2: Y3 | E2: Y4 | F2: Y5
A3: Tier 1 — pilots × price (€) | B3: =Assumptions!B15*Assumptions!B7 | C3: =Assumptions!C15*Assumptions!C7 | D3: =Assumptions!D15*Assumptions!D7 | E3: =Assumptions!E15*Assumptions!E7 | F3: =Assumptions!F15*Assumptions!F7
A4: Tier 2 — customers × ACV (€) | B4: =Assumptions!B16*Assumptions!B8 | C4: =Assumptions!C16*Assumptions!C8 | D4: =Assumptions!D16*Assumptions!D8 | E4: =Assumptions!E16*Assumptions!E8 | F4: =Assumptions!F16*Assumptions!F8
A5: Tier 3 — frameworks × ACV (€) | B5: =Assumptions!B17*Assumptions!B9 | C5: =Assumptions!C17*Assumptions!C9 | D5: =Assumptions!D17*Assumptions!D9 | E5: =Assumptions!E17*Assumptions!E9 | F5: =Assumptions!F17*Assumptions!F9
A7: TOTAL REVENUE (€) | B7: =B3+B4+B5 | C7: =C3+C4+C5 | D7: =D3+D4+D5 | E7: =E3+E4+E5 | F7: =F3+F4+F5
A8: Net new revenue (€) | C8: =C7-B7 | D8: =D7-C7 | E8: =E7-D7 | F8: =F7-E7

Sheet Headcount_Costs
A1: Headcount & Costs
A2: Cost line | B2: Y1 | C2: Y2 | D2: Y3 | E2: Y4 | F2: Y5
A3: Total FTE | B3: =Assumptions!B21+Assumptions!B22+Assumptions!B23+Assumptions!B24+Assumptions!B25+Assumptions!B26 | C3: =Assumptions!C21+Assumptions!C22+Assumptions!C23+Assumptions!C24+Assumptions!C25+Assumptions!C26 | D3: =Assumptions!D21+Assumptions!D22+Assumptions!D23+Assumptions!D24+Assumptions!D25+Assumptions!D26 | E3: =Assumptions!E21+Assumptions!E22+Assumptions!E23+Assumptions!E24+Assumptions!E25+Assumptions!E26 | F3: =Assumptions!F21+Assumptions!F22+Assumptions!F23+Assumptions!F24+Assumptions!F25+Assumptions!F26
A4: People cost (€) | B4: =B3*Assumptions!B27 | C4: =C3*Assumptions!C27 | D4: =D3*Assumptions!D27 | E4: =E3*Assumptions!E27 | F4: =F3*Assumptions!F27
A5: Hosting cost (€) | B5: =(Assumptions!B15+Assumptions!B16+Assumptions!B17)*Assumptions!B31 | C5: =(Assumptions!C15+Assumptions!C16+Assumptions!C17)*Assumptions!C31 | D5: =(Assumptions!D15+Assumptions!D16+Assumptions!D17)*Assumptions!D31 | E5: =(Assumptions!E15+Assumptions!E16+Assumptions!E17)*Assumptions!E31 | F5: =(Assumptions!F15+Assumptions!F16+Assumptions!F17)*Assumptions!F31
A6: S&M non-personnel (€) | B6: =Revenue!B7*Assumptions!B32 | C6: =Revenue!C7*Assumptions!C32 | D6: =Revenue!D7*Assumptions!D32 | E6: =Revenue!E7*Assumptions!E32 | F6: =Revenue!F7*Assumptions!F32
A7: G&A non-personnel (€) | B7: =Revenue!B7*Assumptions!B33 | C7: =Revenue!C7*Assumptions!C33 | D7: =Revenue!D7*Assumptions!D33 | E7: =Revenue!E7*Assumptions!E33 | F7: =Revenue!F7*Assumptions!F33
A8: CS additional COGS (€) | B8: =Revenue!B7*Assumptions!B34 | C8: =Revenue!C7*Assumptions!C34 | D8: =Revenue!D7*Assumptions!D34 | E8: =Revenue!E7*Assumptions!E34 | F8: =Revenue!F7*Assumptions!F34
A10: TOTAL OPERATING COST (€) | B10: =B4+B5+B6+B7+B8 | C10: =C4+C5+C6+C7+C8 | D10: =D4+D5+D6+D7+D8 | E10: =E4+E5+E6+E7+E8 | F10: =F4+F5+F6+F7+F8

Sheet P_and_L
A1: P&L (5 years)
A2: P&L line | B2: Y1 | C2: Y2 | D2: Y3 | E2: Y4 | F2: Y5
A3: Revenue | B3: =Revenue!B7 | C3: =Revenue!C7 | D3: =Revenue!D7 | E3: =Revenue!E7 | F3: =Revenue!F7
A4: COGS | B4: =Headcount_Costs!B5+Headcount_Costs!B8 | C4: =Headcount_Costs!C5+Headcount_Costs!C8 | D4: =Headcount_Costs!D5+Headcount_Costs!D8 | E4: =Headcount_Costs!E5+Headcount_Costs!E8 | F4: =Headcount_Costs!F5+Headcount_Costs!F8
A5: Gross Profit | B5: =B3-B4 | C5: =C3-C4 | D5: =D3-D4 | E5: =E3-E4 | F5: =F3-F4
A6: Gross Margin % | B6: =IFERROR(B5/B3,0) | C6: =IFERROR(C5/C3,0) | D6: =IFERROR(D5/D3,0) | E6: =IFERROR(E5/E3,0) | F6: =IFERROR(F5/F3,0)
A8: Personnel (R&D + S&M + G&A + CS) | B8: =Headcount_Costs!B4 | C8: =Headcount_Costs!C4 | D8: =Headcount_Costs!D4 | E8: =Headcount_Costs!E4 | F8: =Headcount_Costs!F4
A9: S&M non-personnel | B9: =Headcount_Costs!B6 | C9: =Headcount_Costs!C6 | D9: =Headcount_Costs!D6 | E9: =Headcount_Costs!E6 | F9: =Headcount_Costs!F6
A10: G&A non-personnel | B10: =Headcount_Costs!B7 | C10: =Headcount_Costs!C7 | D10: =Headcount_Costs!D7 | E10: =Headcount_Costs!E7 | F10: =Headcount_Costs!F7
A11: Total OPEX | B11: =B8+B9+B10 | C11: =C8+C9+C10 | D11: =D8+D9+D10 | E11: =E8+E9+E10 | F11: =F8+F9+F10
A13: EBITDA | B13: =B5-B11 | C13: =C5-C11 | D13: =D5-D11 | E13: =E5-E11 | F13: =F5-F11
A14: EBITDA margin % | B14: =IFERROR(B13/B3,0) | C14: =IFERROR(C13/C3,0) | D14: =IFERROR(D13/D3,0) | E14: =IFERROR(E13/E3,0) | F14: =IFERROR(F13/F3,0)

Sheet Cash_Flow
A1: Cash Flow & Runway
A2: Cash line | B2: Y1 | C2: Y2 | D2: Y3 | E2: Y4 | F2: Y5
A3: Equity raised (€) | B3: =IF(Assumptions!B39=1,Assumptions!B38,0)+IF(Assumptions!B41=1,Assumptions!B40,0)+IF(Assumptions!B43=1,Assumptions!B42,0) | C3: =IF(Assumptions!B39=2,Assumptions!B38,0)+IF(Assumptions!B41=2,Assumptions!B40,0)+IF(Assumptions!B43=2,Assumptions!B42,0) | D3: =IF(Assumptions!B39=3,Assumptions!B38,0)+IF(Assumptions!B41=3,Assumptions!B40,0)+IF(Assumptions!B43=3,Assumptions!B42,0) | E3: =IF(Assumptions!B39=4,Assumptions!B38,0)+IF(Assumptions!B41=4,Assumptions!B40,0)+IF(Assumptions!B43=4,Assumptions!B42,0) | F3: =IF(Assumptions!B39=5,Assumptions!B38,0)+IF(Assumptions!B41=5,Assumptions!B40,0)+IF(Assumptions!B43=5,Assumptions!B42,0)
A4: EBITDA | B4: =P_and_L!B13 | C4: =P_and_L!C13 | D4: =P_and_L!D13 | E4: =P_and_L!E13 | F4: =P_and_L!F13
A5: Working capital change (10% Δrev) | B5: =-Revenue!B7*0.1 | C5: =-(Revenue!C7-Revenue!B7)*0.1 | D5: =-(Revenue!D7-Revenue!C7)*0.1 | E5: =-(Revenue!E7-Revenue!D7)*0.1 | F5: =-(Revenue!F7-Revenue!E7)*0.1
A7: Net cash flow | B7: =B3+B4+B5 | C7: =C3+C4+C5 | D7: =D3+D4+D5 | E7: =E3+E4+E5 | F7: =F3+F4+F5
A8: Starting cash | B8: 0 | C8: =B9 | D8: =C9 | E8: =D9 | F8: =E9
A9: Ending cash | B9: =B8+B7 | C9: =C8+C7 | D9: =D8+D7 | E9: =E8+E7 | F9: =F8+F7
A10: Runway (months) @ year-end | B10: =IFERROR(IF(B4<0,B9/(-B4/12),999),0) | C10: =IFERROR(IF(C4<0,C9/(-C4/12),999),0) | D10: =IFERROR(IF(D4<0,D9/(-D4/12),999),0) | E10: =IFERROR(IF(E4<0,E9/(-E4/12),999),0) | F10: =IFERROR(IF(F4<0,F9/(-F4/12),999),0)

Sheet KPIs
A1: KPIs dashboard
A2: KPI | B2: Y1 | C2: Y2 | D2: Y3 | E2: Y4 | F2: Y5
A3: ARR end of year (€) | B3: =Revenue!B7 | C3: =Revenue!C7 | D3: =Revenue!D7 | E3: =Revenue!E7 | F3: =Revenue!F7
A4: Net new ARR (€) | B4: =Revenue!B7 | C4: =Revenue!C7-Revenue!B7 | D4: =Revenue!D7-Revenue!C7 | E4: =Revenue!E7-Revenue!D7 | F4: =Revenue!F7-Revenue!E7
A5: Gross margin % | B5: =P_and_L!B6 | C5: =P_and_L!C6 | D5: =P_and_L!D6 | E5: =P_and_L!E6 | F5: =P_and_L!F6
A6: Monthly burn (€) | B6: =IF(P_and_L!B13<0,-P_and_L!B13/12,0) | C6: =IF(P_and_L!C13<0,-P_and_L!C13/12,0) | D6: =IF(P_and_L!D13<0,-P_and_L!D13/12,0) | E6: =IF(P_and_L!E13<0,-P_and_L!E13/12,0) | F6: =IF(P_and_L!F13<0,-P_and_L!F13/12,0)
A7: Active customers | B7: =Assumptions!B15+Assumptions!B16+Assumptions!B17 | C7: =Assumptions!C15+Assumptions!C16+Assumptions!C17 | D7: =Assumptions!D15+Assumptions!D16+Assumptions!D17 | E7: =Assumptions!E15+Assumptions!E16+Assumptions!E17 | F7: =Assumptions!F15+Assumptions!F16+Assumptions!F17
A8: Total headcount | B8: =Headcount_Costs!B3 | C8: =Headcount_Costs!C3 | D8: =Headcount_Costs!D3 | E8: =Headcount_Costs!E3 | F8: =Headcount_Costs!F3
A9: Revenue per FTE (€) | B9: =IFERROR(Revenue!B7/Headcount_Costs!B3,0) | C9: =IFERROR(Revenue!C7/Headcount_Costs!C3,0) | D9: =IFERROR(Revenue!D7/Headcount_Costs!D3,0) | E9: =IFERROR(Revenue!E7/Headcount_Costs!E3,0) | F9: =IFERROR(Revenue!F7/Headcount_Costs!F3,0)
A10: Cash at year-end (€) | B10: =Cash_Flow!B9 | C10: =Cash_Flow!C9 | D10: =Cash_Flow!D9 | E10: =Cash_Flow!E9 | F10: =Cash_Flow!F9
A12: Y5 ARR scenarios (sensitivity on Tier 2/3 counts)
A13: Scenario | B13: Multiplier | C13: Y5 ARR (€)
A14: Conservative | B14: 0.6 | C14: =Revenue!F7*0.6
A15: Base | B15: 1 | C15: =Revenue!F7
A16: Aggressive | B16: 1.5 | C16: =Revenue!F7*1.5
